type_templating/__init__.py
type_templating/_version.py
type_templating-0.2.0.dist-info/LICENSE
type_templating-0.2.0.dist-info/METADATA
type_templating-0.2.0.dist-info/WHEEL
type_templating-0.2.0.dist-info/top_level.txt
type_templating-0.2.0.dist-info/RECORD
