Metadata-Version: 2.1
Name: type-templating
Version: 0.2.0
Summary: C++-style type templating for Python
Home-page: http://type_templating.readthedocs.io
Author: Eric Wieser
License: MIT
Project-URL: Bug Tracker, https://github.com/eric-wieser/type_templating/issues
Project-URL: Source Code, https://github.com/eric-wieser/type_templating
Platform: UNKNOWN
Classifier: License :: OSI Approved :: MIT License
Classifier: Programming Language :: Python :: 3
Requires-Python: >=3.5
